bullycomp.py
bullycomp-1.0.0.dist-info/METADATA
bullycomp-1.0.0.dist-info/WHEEL
bullycomp-1.0.0.dist-info/entry_points.txt
bullycomp-1.0.0.dist-info/top_level.txt
bullycomp-1.0.0.dist-info/RECORD
