Metadata-Version: 2.1
Name: bullycomp
Version: 1.0.0
Summary: A package compares the number of bullying incidents each year
Home-page: https://github.com/DaichiKitazawa/bully
Author: daichi kitazawa
Author-email: s2022008@stu.musashino-u.ac.jp
License: UNKNOWN
Project-URL: Bug Tracker, https://github.com/DaichiKitazawa/bully
Platform: UNKNOWN
Classifier: Programming Language :: Python :: 3
Classifier: License :: OSI Approved :: MIT License
Classifier: Operating System :: OS Independent
Requires-Python: >=3.7
